README.md
setup.cfg
setup.py
gnutty.egg-info/PKG-INFO
gnutty.egg-info/SOURCES.txt
gnutty.egg-info/dependency_links.txt
gnutty.egg-info/top_level.txt
srv/__init__.py
srv/auth.py
srv/constants.py
srv/example_server.py
srv/exit.py
srv/gnutty.py
srv/gnuttycore.py
srv/logger.py
srv/methods.py
srv/request.py
srv/request_methods.py
srv/singleton.py