Metadata-Version: 2.1
Name: gnutty
Version: 0.0.1
Summary: Pure Python REST HTTP Server
Home-page: https://github.com/atomicfruitcake/gnutty
Author: atomicfruitcake
License: MIT
Download-URL: https://github.com/atomicfruitcake/gnutty/archive/v0.0.1.tar.gz
Keywords: server,http,rest,api
Platform: UNKNOWN
Classifier: Development Status :: 3 - Alpha
Classifier: Intended Audience :: Developers
Classifier: License :: OSI Approved :: MIT License
Classifier: Programming Language :: Python :: 3
Classifier: Programming Language :: Python :: 3.7
